LICENSE
README.md
setup.py
dash_manager/__init__.py
dash_manager/__main__.py
dash_manager/info.py
dash_manager.egg-info/PKG-INFO
dash_manager.egg-info/SOURCES.txt
dash_manager.egg-info/dependency_links.txt
dash_manager.egg-info/entry_points.txt
dash_manager.egg-info/requires.txt
dash_manager.egg-info/top_level.txt
dash_manager/commands/__init__.py
dash_manager/commands/new.py
dash_manager/manager/__init__.py
dash_manager/manager/base.py
dash_manager/manager/menu.py
dash_manager/manager/template.py