Metadata-Version: 2.1
Name: dash-manager
Version: 1.0.1
Summary: A tool for combining Dash apps on a single server
Home-page: https://github.com/stpnvkirill/dash-manager
Author: Kirill Stepanov
Author-email: stpnv.kirill.o@gmail.com
Classifier: Programming Language :: Python :: 3
Classifier: License :: OSI Approved :: MIT License
Classifier: Operating System :: OS Independent
License-File: LICENSE
